herodote_auth/__init__.py
herodote_auth/middleware.py
herodote_auth-0.0.1.dev22.dist-info/AUTHORS
herodote_auth-0.0.1.dev22.dist-info/LICENSE
herodote_auth-0.0.1.dev22.dist-info/METADATA
herodote_auth-0.0.1.dev22.dist-info/WHEEL
herodote_auth-0.0.1.dev22.dist-info/entry_points.txt
herodote_auth-0.0.1.dev22.dist-info/pbr.json
herodote_auth-0.0.1.dev22.dist-info/top_level.txt
herodote_auth-0.0.1.dev22.dist-info/RECORD
