Metadata-Version: 2.1
Name: herodote-auth
Version: 0.0.1.dev22
Summary: Auth middleware for swift and herodote
Home-page: https://github.com/osallou/herodote
Author: Olivier Sallou
Author-email: olivier.sallou@irisa.fr
License: UNKNOWN
Platform: UNKNOWN
Classifier: Development Status :: 5 - Production/Stable
Classifier: Environment :: OpenStack
Classifier: Intended Audience :: Information Technology
Classifier: Intended Audience :: System Administrators
Classifier: License :: OSI Approved :: Apache Software License
Classifier: Operating System :: POSIX :: Linux
Classifier: Programming Language :: Python
Classifier: Programming Language :: Python :: 3
Requires-Dist: PyJWT
Requires-Dist: requests
